{
  "url": "https://en.wikipedia.org/wiki/Computational_intelligence",
  "title": "Computational intelligence",
  "html": "<!DOCTYPE html>\n<html class=\"client-nojs\" dir=\"ltr\" lang=\"en\">\n<head>\n<meta charset=\"utf-8\"/>\n<title>Computational intelligence - Wikipedia</title>\n<script>document.documentElement.className = document.documentElement.className.replace( /(^|\\s)client-nojs(\\s|$)/, \"$1client-js$2\" );</script>\n<script>(window.RLQ=window.RLQ||[]).push(function(){mw.config.set({\"wgCanonicalNamespace\":\"\",\"wgCanonicalSpecialPageName\":false,\"wgNamespaceNumber\":0,\"wgPageName\":\"Computational_intelligence\",\"wgTitle\":\"Computational intelligence\",\"wgCurRevisionId\":865907791,\"wgRevisionId\":865907791,\"wgArticleId\":1563306,\"wgIsArticle\":true,\"wgIsRedirect\":false,\"wgAction\":\"view\",\"wgUserName\":null,\"wgUserGroups\":[\"*\"],\"wgCategories\":[\"Use mdy dates from October 2016\",\"Use American English from October 2016\",\"All Wikipedia articles written in American English\",\"Articles lacking in-text citations from July 2012\",\"All articles lacking in-text citations\",\"Wikipedia articles needing page number citations from November 2016\",\"All articles with specifically marked weasel-worded phrases\",\"Articles with specifically marked weasel-worded phrases from October 2017\",\"All articles with unsourced statements\",\"Articles with unsourced statements from October 2017\",\"Wikipedia articles needing clarification from October 2017\",\"Articles with unsourced statements from November 2016\",\"Artificial intelligence\"],\"wgBreakFrames\":false,\"wgPageContentLanguage\":\"en\",\"wgPageContentModel\":\"wikitext\",\"wgSeparatorTransformTable\":[\"\",\"\"],\"wgDigitTransformTable\":[\"\",\"\"],\"wgDefaultDateFormat\":\"dmy\",\"wgMonthNames\":[\"\",\"January\",\"February\",\"March\",\"April\",\"May\",\"June\",\"July\",\"August\",\"September\",\"October\",\"November\",\"December\"],\"wgMonthNamesShort\":[\"\",\"Jan\",\"Feb\",\"Mar\",\"Apr\",\"May\",\"Jun\",\"Jul\",\"Aug\",\"Sep\",\"Oct\",\"Nov\",\"Dec\"],\"wgRelevantPageName\":\"Computational_intelligence\",\"wgRelevantArticleId\":1563306,\"wgRequestId\":\"XHMAHwpAMEoAAGvnMLwAAAAK\",\"wgCSPNonce\":false,\"wgIsProbablyEditable\":true,\"wgRelevantPageIsProbablyEditable\":true,\"wgRestrictionEdit\":[],\"wgRestrictionMove\":[],\"wgFlaggedRevsParams\":{\"tags\":{}},\"wgStableRevisionId\":null,\"wgCategoryTreePageCategoryOptions\":\"{\\\"mode\\\":0,\\\"hideprefix\\\":20,\\\"showcount\\\":true,\\\"namespaces\\\":false}\",\"wgWikiEditorEnabledModules\":[],\"wgBetaFeaturesFeatures\":[],\"wgMediaViewerOnClick\":true,\"wgMediaViewerEnabledByDefault\":true,\"wgPopupsShouldSendModuleToUser\":true,\"wgPopupsConflictsWithNavPopupGadget\":false,\"wgVisualEditor\":{\"pageLanguageCode\":\"en\",\"pageLanguageDir\":\"ltr\",\"pageVariantFallbacks\":\"en\",\"usePageImages\":true,\"usePageDescriptions\":true},\"wgMFIsPageContentModelEditable\":true,\"wgMFEnableFontChanger\":true,\"wgMFDisplayWikibaseDescriptions\":{\"search\":true,\"nearby\":true,\"watchlist\":true,\"tagline\":false},\"wgRelatedArticles\":null,\"wgRelatedArticlesUseCirrusSearch\":true,\"wgRelatedArticlesOnlyUseCirrusSearch\":false,\"wgWMESchemaEditAttemptStepOversample\":false,\"wgPoweredByHHVM\":true,\"wgULSCurrentAutonym\":\"English\",\"wgNoticeProject\":\"wikipedia\",\"wgCentralNoticeCookiesToDelete\":[],\"wgCentralNoticeCategoriesUsingLegacy\":[\"Fundraising\",\"fundraising\"],\"wgWikibaseItemId\":\"Q1122090\",\"wgScoreNoteLanguages\":{\"arabic\":\"العربية\",\"catalan\":\"català\",\"deutsch\":\"Deutsch\",\"english\":\"English\",\"espanol\":\"español\",\"italiano\":\"italiano\",\"nederlands\":\"Nederlands\",\"norsk\":\"norsk\",\"portugues\":\"português\",\"suomi\":\"suomi\",\"svenska\":\"svenska\",\"vlaams\":\"West-Vlams\"},\"wgScoreDefaultNoteLanguage\":\"nederlands\",\"wgCentralAuthMobileDomain\":false,\"wgCodeMirrorEnabled\":true,\"wgVisualEditorToolbarScrollOffset\":0,\"wgVisualEditorUnsupportedEditParams\":[\"undo\",\"undoafter\",\"veswitched\"],\"wgEditSubmitButtonLabelPublish\":true,\"oresWikiId\":\"enwiki\",\"oresBaseUrl\":\"http://ores.discovery.wmnet:8081/\",\"oresApiVersion\":3});mw.loader.state({\"ext.gadget.charinsert-styles\":\"ready\",\"ext.globalCssJs.user.styles\":\"ready\",\"ext.globalCssJs.site.styles\":\"ready\",\"site.styles\":\"ready\",\"noscript\":\"ready\",\"user.styles\":\"ready\",\"ext.globalCssJs.user\":\"ready\",\"ext.globalCssJs.site\":\"ready\",\"user\":\"ready\",\"user.options\":\"ready\",\"user.tokens\":\"loading\",\"ext.cite.styles\":\"ready\",\"mediawiki.legacy.shared\":\"ready\",\"mediawiki.legacy.commonPrint\":\"ready\",\"mediawiki.toc.styles\":\"ready\",\"wikibase.client.init\":\"ready\",\"ext.visualEditor.desktopArticleTarget.noscript\":\"ready\",\"ext.uls.interlanguage\":\"ready\",\"ext.wikimediaBadges\":\"ready\",\"ext.3d.styles\":\"ready\",\"mediawiki.skinning.interface\":\"ready\",\"skins.vector.styles\":\"ready\"});mw.loader.implement(\"user.tokens@0tffind\",function($,jQuery,require,module){/*@nomin*/mw.user.tokens.set({\"editToken\":\"+\\\\\",\"patrolToken\":\"+\\\\\",\"watchToken\":\"+\\\\\",\"csrfToken\":\"+\\\\\"});\n});RLPAGEMODULES=[\"ext.cite.ux-enhancements\",\"site\",\"mediawiki.page.startup\",\"mediawiki.page.ready\",\"mediawiki.toc\",\"mediawiki.searchSuggest\",\"ext.gadget.teahouse\",\"ext.gadget.ReferenceTooltips\",\"ext.gadget.watchlist-notice\",\"ext.gadget.DRN-wizard\",\"ext.gadget.charinsert\",\"ext.gadget.refToolbar\",\"ext.gadget.extra-toolbar-buttons\",\"ext.gadget.switcher\",\"ext.centralauth.centralautologin\",\"mmv.head\",\"mmv.bootstrap.autostart\",\"ext.popups\",\"ext.visualEditor.desktopArticleTarget.init\",\"ext.visualEditor.targetLoader\",\"ext.eventLogging\",\"ext.wikimediaEvents\",\"ext.navigationTiming\",\"ext.uls.eventlogger\",\"ext.uls.init\",\"ext.uls.compactlinks\",\"ext.uls.interface\",\"ext.quicksurveys.init\",\"ext.centralNotice.geoIP\",\"ext.centralNotice.startUp\",\"skins.vector.js\"];mw.loader.load(RLPAGEMODULES);});</script>\n<link href=\"/w/load.php?debug=false&amp;lang=en&amp;modules=ext.3d.styles%7Cext.cite.styles%7Cext.uls.interlanguage%7Cext.visualEditor.desktopArticleTarget.noscript%7Cext.wikimediaBadges%7Cmediawiki.legacy.commonPrint%2Cshared%7Cmediawiki.skinning.interface%7Cmediawiki.toc.styles%7Cskins.vector.styles%7Cwikibase.client.init&amp;only=styles&amp;skin=vector\" rel=\"stylesheet\"/>\n<script async=\"\" src=\"/w/load.php?debug=false&amp;lang=en&amp;modules=startup&amp;only=scripts&amp;skin=vector\"></script>\n<meta content=\"\" name=\"ResourceLoaderDynamicStyles\"/>\n<link href=\"/w/load.php?debug=false&amp;lang=en&amp;modules=ext.gadget.charinsert-styles&amp;only=styles&amp;skin=vector\" rel=\"stylesheet\"/>\n<link href=\"/w/load.php?debug=false&amp;lang=en&amp;modules=site.styles&amp;only=styles&amp;skin=vector\" rel=\"stylesheet\"/>\n<meta content=\"MediaWiki 1.33.0-wmf.18\" name=\"generator\"/>\n<meta content=\"origin\" name=\"referrer\"/>\n<meta content=\"origin-when-crossorigin\" name=\"referrer\"/>\n<meta content=\"origin-when-cross-origin\" name=\"referrer\"/>\n<link href=\"android-app://org.wikipedia/http/en.m.wikipedia.org/wiki/Computational_intelligence\" rel=\"alternate\"/>\n<link href=\"/w/index.php?title=Computational_intelligence&amp;action=edit\" rel=\"alternate\" title=\"Edit this page\" type=\"application/x-wiki\"/>\n<link href=\"/w/index.php?title=Computational_intelligence&amp;action=edit\" rel=\"edit\" title=\"Edit this page\"/>\n<link href=\"/static/apple-touch/wikipedia.png\" rel=\"apple-touch-icon\"/>\n<link href=\"/static/favicon/wikipedia.ico\" rel=\"shortcut icon\"/>\n<link href=\"/w/opensearch_desc.php\" rel=\"search\" title=\"Wikipedia (en)\" type=\"application/opensearchdescription+xml\"/>\n<link href=\"//en.wikipedia.org/w/api.php?action=rsd\" rel=\"EditURI\" type=\"application/rsd+xml\"/>\n<link href=\"//creativecommons.org/licenses/by-sa/3.0/\" rel=\"license\"/>\n<link href=\"https://en.wikipedia.org/wiki/Computational_intelligence\" rel=\"canonical\"/>\n<link href=\"//login.wikimedia.org\" rel=\"dns-prefetch\"/>\n<link href=\"//meta.wikimedia.org\" rel=\"dns-prefetch\"/>\n<!--[if lt IE 9]><script src=\"/w/load.php?debug=false&amp;lang=en&amp;modules=html5shiv&amp;only=scripts&amp;skin=vector&amp;sync=1\"></script><![endif]-->\n</head>\n<body class=\"mediawiki ltr sitedir-ltr mw-hide-empty-elt ns-0 ns-subject mw-editable page-Computational_intelligence rootpage-Computational_intelligence skin-vector action-view\"> <div class=\"noprint\" id=\"mw-page-base\"></div>\n<div class=\"noprint\" id=\"mw-head-base\"></div>\n<div class=\"mw-body\" id=\"content\" role=\"main\">\n<a id=\"top\"></a>\n<div class=\"mw-body-content\" id=\"siteNotice\"><!-- CentralNotice --></div><div class=\"mw-indicators mw-body-content\">\n</div>\n<h1 class=\"firstHeading\" id=\"firstHeading\" lang=\"en\">Computational intelligence</h1> <div class=\"mw-body-content\" id=\"bodyContent\">\n<div class=\"noprint\" id=\"siteSub\">From Wikipedia, the free encyclopedia</div> <div id=\"contentSub\"></div>\n<div id=\"jump-to-nav\"></div> <a class=\"mw-jump-link\" href=\"#mw-head\">Jump to navigation</a>\n<a class=\"mw-jump-link\" href=\"#p-search\">Jump to search</a>\n<div class=\"mw-content-ltr\" dir=\"ltr\" id=\"mw-content-text\" lang=\"en\"><div class=\"mw-parser-output\"><div class=\"hatnote navigation-not-searchable\" role=\"note\">For the journal, see <a href=\"/wiki/Computational_Intelligence_(journal)\" title=\"Computational Intelligence (journal)\">Computational Intelligence (journal)</a>.</div> <div class=\"hatnote navigation-not-searchable\" role=\"note\">For a broader coverage of this topic, see <a href=\"/wiki/Artificial_intelligence\" title=\"Artificial intelligence\">Artificial intelligence</a>.</div>\n<p class=\"mw-empty-elt\">\n</p>\n<table class=\"box-More_footnotes plainlinks metadata ambox ambox-style ambox-More_footnotes\" role=\"presentation\"><tbody><tr><td class=\"mbox-image\"><div style=\"width:52px\"><img alt=\"\" data-file-height=\"48\" data-file-width=\"48\" decoding=\"async\" height=\"40\" src=\"//upload.wikimedia.org/wikipedia/commons/thumb/a/a4/Text_document_with_red_question_mark.svg/40px-Text_document_with_red_question_mark.svg.png\" srcset=\"//upload.wikimedia.org/wikipedia/commons/thumb/a/a4/Text_document_with_red_question_mark.svg/60px-Text_document_with_red_question_mark.svg.png 1.5x, //upload.wikimedia.org/wikipedia/commons/thumb/a/a4/Text_document_with_red_question_mark.svg/80px-Text_document_with_red_question_mark.svg.png 2x\" width=\"40\"/></div></td><td class=\"mbox-text\"><div class=\"mbox-text-span\">This article includes a <a href=\"/wiki/Wikipedia:Citing_sources\" title=\"Wikipedia:Citing sources\">list of references</a>, but <b>its sources remain unclear</b> because it has <b>insufficient <a href=\"/wiki/Wikipedia:Citing_sources#Inline_citations\" title=\"Wikipedia:Citing sources\">inline citations</a></b>.<span class=\"hide-when-compact\"> Please help to <a class=\"mw-redirect\" href=\"/wiki/Wikipedia:WikiProject_Fact_and_Reference_Check\" title=\"Wikipedia:WikiProject Fact and Reference Check\">improve</a> this article by <a href=\"/wiki/Wikipedia:When_to_cite\" title=\"Wikipedia:When to cite\">introducing</a> more precise citations.</span> <small class=\"date-container\"><i>(<span class=\"date\">July 2012</span>)</i></small><small class=\"hide-when-compact\"><i> (<a href=\"/wiki/Help:Maintenance_template_removal\" title=\"Help:Maintenance template removal\">Learn how and when to remove this template message</a>)</i></small></div></td></tr></tbody></table>\n<p>The expression <b>computational intelligence</b> (<b>CI</b>) usually refers to the ability of a <a href=\"/wiki/Computer\" title=\"Computer\">computer</a> to learn a specific task from data or experimental observation. Even though it is commonly considered a synonym of <a href=\"/wiki/Soft_computing\" title=\"Soft computing\">soft computing</a>, there is still no commonly accepted definition of computational intelligence.\n</p><p>Generally, computational intelligence is a set of nature-inspired computational methodologies and approaches to address complex real-world problems to which mathematical or traditional modelling can be useless for a few reasons: the processes might be too complex for mathematical reasoning, it might contain some uncertainties during the process, or the process might simply be stochastic in nature.<sup class=\"reference\" id=\"cite_ref-Siddique_&amp;_Adeli_1-0\"><a href=\"#cite_note-Siddique_&amp;_Adeli-1\">[1]</a></sup><sup class=\"noprint Inline-Template\" style=\"white-space:nowrap;\">[<i><a href=\"/wiki/Wikipedia:Citing_sources\" title=\"Wikipedia:Citing sources\"><span title=\"This citation requires a reference to the specific page or range of pages in which the material appears. (November 2016)\">page needed</span></a></i>]</sup> Indeed, many real-life problems cannot be translated into binary language (unique values of 0 and 1) for computers to process it. Computational Intelligence therefore provides solutions for such problems.\n</p><p>The methods used are close to the human's way of reasoning, i.e. it uses inexact and incomplete knowledge, and it is able to produce control actions in an adaptive way. CI therefore uses a combination of five main complementary techniques.<sup class=\"reference\" id=\"cite_ref-Siddique_&amp;_Adeli_1-1\"><a href=\"#cite_note-Siddique_&amp;_Adeli-1\">[1]</a></sup> The <a href=\"/wiki/Fuzzy_logic\" title=\"Fuzzy logic\">fuzzy logic</a> which enables the computer to <a class=\"mw-redirect\" href=\"/wiki/Natural_language_understanding\" title=\"Natural language understanding\">understand natural language</a>,<sup class=\"reference\" id=\"cite_ref-2\"><a href=\"#cite_note-2\">[2]</a></sup><sup class=\"noprint Inline-Template\" style=\"white-space:nowrap;\">[<i><a href=\"/wiki/Wikipedia:Citing_sources\" title=\"Wikipedia:Citing sources\"><span title=\"This citation requires a reference to the specific page or range of pages in which the material appears. (November 2016)\">page needed</span></a></i>]</sup><sup class=\"reference\" id=\"cite_ref-Fuzzy_Logic_3-0\"><a href=\"#cite_note-Fuzzy_Logic-3\">[3]</a></sup> <a href=\"/wiki/Artificial_neural_network\" title=\"Artificial neural network\">artificial neural networks</a> which permits the system to learn experiential data by operating like the biological one, <a href=\"/wiki/Evolutionary_computation\" title=\"Evolutionary computation\">evolutionary computing</a>, which is based on the process of natural selection, learning theory, and probabilistic methods which helps dealing with uncertainty imprecision.<sup class=\"reference\" id=\"cite_ref-Siddique_&amp;_Adeli_1-2\"><a href=\"#cite_note-Siddique_&amp;_Adeli-1\">[1]</a></sup>\n</p><p>Except those main principles, currently popular approaches include biologically inspired algorithms such as <a href=\"/wiki/Swarm_intelligence\" title=\"Swarm intelligence\">swarm intelligence</a><sup class=\"reference\" id=\"cite_ref-4\"><a href=\"#cite_note-4\">[4]</a></sup> and <a href=\"/wiki/Artificial_immune_system\" title=\"Artificial immune system\">artificial immune systems</a>, which can be seen as a part of <a href=\"/wiki/Evolutionary_computation\" title=\"Evolutionary computation\">evolutionary computation</a>, image processing, data mining, natural language processing, and artificial intelligence, which tends to be confused with Computational Intelligence. But although both Computational Intelligence (CI) and <a href=\"/wiki/Artificial_intelligence\" title=\"Artificial intelligence\">Artificial Intelligence</a> (AI) seek similar goals, there's a clear distinction between them<sup class=\"noprint Inline-Template\" style=\"margin-left:0.1em; white-space:nowrap;\">[<i><a href=\"/wiki/Wikipedia:Manual_of_Style/Words_to_watch#Unsupported_attributions\" title=\"Wikipedia:Manual of Style/Words to watch\"><span title=\"The material near this tag may use weasel words or too-vague attribution. (October 2017)\">according to whom?</span></a></i>]</sup><sup class=\"noprint Inline-Template Template-Fact\" style=\"white-space:nowrap;\">[<i><a href=\"/wiki/Wikipedia:Citation_needed\" title=\"Wikipedia:Citation needed\"><span title=\"This claim needs references to reliable sources. (October 2017)\">citation needed</span></a></i>]</sup>.\n</p><p>Computational Intelligence is thus a way of performing like human beings<sup class=\"noprint Inline-Template Template-Fact\" style=\"white-space:nowrap;\">[<i><a href=\"/wiki/Wikipedia:Citation_needed\" title=\"Wikipedia:Citation needed\"><span title=\"This claim needs references to reliable sources. (October 2017)\">citation needed</span></a></i>]</sup>. Indeed, the characteristic of \"intelligence\" is usually attributed<sup class=\"noprint Inline-Template\" style=\"white-space:nowrap;\">[<i><a href=\"/wiki/Wikipedia:Manual_of_Style/Words_to_watch#Unsupported_attributions\" title=\"Wikipedia:Manual of Style/Words to watch\"><span title=\"The material near this tag may use weasel words or too-vague attribution. (October 2017)\">by whom?</span></a></i>]</sup> to humans. More recently, many products and items also claim to be \"intelligent\", an attribute which is directly linked to the reasoning and decision making<sup class=\"noprint Inline-Template\" style=\"white-space:nowrap;\">[<i><a href=\"/wiki/Wikipedia:Please_clarify\" title=\"Wikipedia:Please clarify\"><span title=\"The text near this tag needs further explanation. (October 2017)\">further explanation needed</span></a></i>]</sup>.\n</p>\n<div class=\"toc\" id=\"toc\"><input class=\"toctogglecheckbox\" id=\"toctogglecheckbox\" role=\"button\" style=\"display:none\" type=\"checkbox\"/><div class=\"toctitle\" dir=\"ltr\" lang=\"en\"><h2>Contents</h2><span class=\"toctogglespan\"><label class=\"toctogglelabel\" for=\"toctogglecheckbox\"></label></span></div>\n<ul>\n<li class=\"toclevel-1 tocsection-1\"><a href=\"#History[5]\"><span class=\"tocnumber\">1</span> <span class=\"toctext\">History<sup>[5]</sup></span></a></li>\n<li class=\"toclevel-1 tocsection-2\"><a href=\"#Difference_between_Computational_and_Artificial_Intelligence\"><span class=\"tocnumber\">2</span> <span class=\"toctext\">Difference between Computational and Artificial Intelligence</span></a></li>\n<li class=\"toclevel-1 tocsection-3\"><a href=\"#The_five_main_principles_of_CI_and_its_applications\"><span class=\"tocnumber\">3</span> <span class=\"toctext\">The five main principles of CI and its applications</span></a>\n<ul>\n<li class=\"toclevel-2 tocsection-4\"><a href=\"#Fuzzy_logic\"><span class=\"tocnumber\">3.1</span> <span class=\"toctext\">Fuzzy logic</span></a></li>\n<li class=\"toclevel-2 tocsection-5\"><a href=\"#Neural_networks\"><span class=\"tocnumber\">3.2</span> <span class=\"toctext\">Neural networks</span></a></li>\n<li class=\"toclevel-2 tocsection-6\"><a href=\"#Evolutionary_computation\"><span class=\"tocnumber\">3.3</span> <span class=\"toctext\">Evolutionary computation</span></a></li>\n<li class=\"toclevel-2 tocsection-7\"><a href=\"#Learning_theory\"><span class=\"tocnumber\">3.4</span> <span class=\"toctext\">Learning theory</span></a></li>\n<li class=\"toclevel-2 tocsection-8\"><a href=\"#Probabilistic_methods\"><span class=\"tocnumber\">3.5</span> <span class=\"toctext\">Probabilistic methods</span></a></li>\n</ul>\n</li>\n<li class=\"toclevel-1 tocsection-9\"><a href=\"#See_also\"><span class=\"tocnumber\">4</span> <span class=\"toctext\">See also</span></a></li>\n<li class=\"toclevel-1 tocsection-10\"><a href=\"#Notes\"><span class=\"tocnumber\">5</span> <span class=\"toctext\">Notes</span></a></li>\n<li class=\"toclevel-1 tocsection-11\"><a href=\"#Publications\"><span class=\"tocnumber\">6</span> <span class=\"toctext\">Publications</span></a></li>\n<li class=\"toclevel-1 tocsection-12\"><a href=\"#References\"><span class=\"tocnumber\">7</span> <span class=\"toctext\">References</span></a></li>\n</ul>\n</div>\n<h2><span id=\"History.5B5.5D\"></span><span class=\"mw-headline\" id=\"History[5]\">History<sup class=\"reference\" id=\"cite_ref-5\"><a href=\"#cite_note-5\">[5]</a></sup></span><span class=\"mw-editsection\"><span class=\"mw-editsection-bracket\">[</span><a href=\"/w/index.php?title=Computational_intelligence&amp;action=edit&amp;section=1\" title=\"Edit section: History[5]\">edit</a><span class=\"mw-editsection-bracket\">]</span></span></h2>\n<p>The notion of Computational Intelligence was first used by the IEEE Neural Networks Council in 1990. This Council was founded in the 1980s by a group of researchers interested in the development of biological and artificial neural networks. On November 21, 2001, the IEEE Neural Networks Council became the IEEE Neural Networks Society, to become the <a href=\"/wiki/IEEE_Computational_Intelligence_Society\" title=\"IEEE Computational Intelligence Society\">IEEE Computational Intelligence Society</a> two years later by including new areas of interest such as fuzzy systems and evolutionary computation, which they related to Computational Intelligence in 2011 (Dote and Ovaska).\n</p><p>But the first clear definition of Computational Intelligence was introduced by Bezdek in 1994:<sup class=\"reference\" id=\"cite_ref-Siddique_&amp;_Adeli_1-3\"><a href=\"#cite_note-Siddique_&amp;_Adeli-1\">[1]</a></sup> a system is called computationally intelligent if it deals with low-level data such as numerical data, has a pattern-recognition component and does not use knowledge in the AI sense, and additionally when it begins to exhibit computational adaptively, fault tolerance, speed approaching human-like turnaround and error rates that approximate human performance.\n</p><p>Bezdek and Marks (1993) clearly differentiated CI from AI, by arguing that the first one is based on <a href=\"/wiki/Soft_computing\" title=\"Soft computing\">soft computing</a> methods, whereas AI is based on hard computing ones.\n</p>\n<h2><span class=\"mw-headline\" id=\"Difference_between_Computational_and_Artificial_Intelligence\">Difference between Computational and Artificial Intelligence</span><span class=\"mw-editsection\"><span class=\"mw-editsection-bracket\">[</span><a href=\"/w/index.php?title=Computational_intelligence&amp;action=edit&amp;section=2\" title=\"Edit section: Difference between Computational and Artificial Intelligence\">edit</a><span class=\"mw-editsection-bracket\">]</span></span></h2>\n<p>Although Artificial Intelligence and Computational Intelligence seek a similar long-term goal: reach <a href=\"/wiki/Artificial_general_intelligence\" title=\"Artificial general intelligence\">general intelligence</a>, which is the intelligence of a machine that could perform any intellectual task that a human being can; there's a clear difference between them. According to Bezdek (1994), Computational Intelligence is a subset of Artificial Intelligence.\n</p><p>There are two types of machine intelligence: the artificial one based on hard computing techniques and the computational one based on soft computing methods, which enable adaptation to many situations.\n</p><p>Hard computing techniques work following binary logic based on only two values (the Booleans true or false, 0 or 1) on which modern computers are based. One problem with this logic is that our natural language cannot always be translated easily into absolute terms of 0 and 1. Soft computing techniques, based on fuzzy logic can be useful here.<sup class=\"reference\" id=\"cite_ref-6\"><a href=\"#cite_note-6\">[6]</a></sup> Much closer to the way the human brain works by aggregating data to partial truths (Crisp/fuzzy systems), this logic is one of the main exclusive aspects of CI.\n</p><p>Within the same principles of fuzzy and binary <i>logics</i> follow crispy and fuzzy <i>systems</i>.<sup class=\"reference\" id=\"cite_ref-7\"><a href=\"#cite_note-7\">[7]</a></sup> Crisp logic is a part of artificial intelligence principles and consists of either including an element in a set, or not, whereas fuzzy systems (CI) enable elements to be partially in a set. Following this logic, each element can be given a degree of membership (from 0 to 1) and not exclusively one of these 2 values.<sup class=\"reference\" id=\"cite_ref-8\"><a href=\"#cite_note-8\">[8]</a></sup>\n</p>\n<h2><span class=\"mw-headline\" id=\"The_five_main_principles_of_CI_and_its_applications\">The five main principles of CI and its applications</span><span class=\"mw-editsection\"><span class=\"mw-editsection-bracket\">[</span><a href=\"/w/index.php?title=Computational_intelligence&amp;action=edit&amp;section=3\" title=\"Edit section: The five main principles of CI and its applications\">edit</a><span class=\"mw-editsection-bracket\">]</span></span></h2>\n<p>The main applications of Computational Intelligence include <a href=\"/wiki/Computer_science\" title=\"Computer science\">computer science</a>, engineering, <a href=\"/wiki/Data_analysis\" title=\"Data analysis\">data analysis</a> and <a class=\"mw-redirect\" href=\"/wiki/Bio-medicine\" title=\"Bio-medicine\">bio-medicine</a>.\n</p>\n<h3><span class=\"mw-headline\" id=\"Fuzzy_logic\">Fuzzy logic</span><span class=\"mw-editsection\"><span class=\"mw-editsection-bracket\">[</span><a href=\"/w/index.php?title=Computational_intelligence&amp;action=edit&amp;section=4\" title=\"Edit section: Fuzzy logic\">edit</a><span class=\"mw-editsection-bracket\">]</span></span></h3>\n<p>As explained before, <a href=\"/wiki/Fuzzy_logic\" title=\"Fuzzy logic\">fuzzy logic</a>, one of CI's main principles, consists in measurements and process modelling made for real life's complex processes.<sup class=\"reference\" id=\"cite_ref-Fuzzy_Logic_3-1\"><a href=\"#cite_note-Fuzzy_Logic-3\">[3]</a></sup> It can face incompleteness, and most importantly ignorance of data in a process model, contrarily to Artificial Intelligence, which requires exact knowledge.\n</p><p>This technique tends to apply to a wide range of domains such as control, <a class=\"mw-redirect\" href=\"/wiki/Image_processing\" title=\"Image processing\">image processing</a> and decision making. But it is also well introduced in the field of household appliances with washing machines, microwave ovens, etc. We can face it too when using a video camera, where it helps stabilizing the image while holding the camera unsteadily. Other areas such as medical diagnostics, foreign exchange trading and business strategy selection are apart from this principle's numbers of applications.<sup class=\"reference\" id=\"cite_ref-Siddique_&amp;_Adeli_1-4\"><a href=\"#cite_note-Siddique_&amp;_Adeli-1\">[1]</a></sup>\n</p><p>Fuzzy logic is mainly useful for approximate reasoning, and doesn't have learning abilities,<sup class=\"reference\" id=\"cite_ref-Siddique_&amp;_Adeli_1-5\"><a href=\"#cite_note-Siddique_&amp;_Adeli-1\">[1]</a></sup> a qualification much needed that human beings have.<sup class=\"noprint Inline-Template Template-Fact\" style=\"white-space:nowrap;\">[<i><a href=\"/wiki/Wikipedia:Citation_needed\" title=\"Wikipedia:Citation needed\"><span title=\"This claim needs references to reliable sources. (November 2016)\">citation needed</span></a></i>]</sup> It enables them to improve themselves by learning from their previous mistakes.\n</p>\n<h3><span class=\"mw-headline\" id=\"Neural_networks\">Neural networks</span><span class=\"mw-editsection\"><span class=\"mw-editsection-bracket\">[</span><a href=\"/w/index.php?title=Computational_intelligence&amp;action=edit&amp;section=5\" title=\"Edit section: Neural networks\">edit</a><span class=\"mw-editsection-bracket\">]</span></span></h3>\n<p>This is why CI experts work on the development of <a href=\"/wiki/Artificial_neural_network\" title=\"Artificial neural network\">artificial neural networks</a> based on the <a class=\"mw-redirect\" href=\"/wiki/Biological_neural_network\" title=\"Biological neural network\">biological ones</a>, which can be defined by 3 main components: the cell-body which processes the information, the axon, which is a device enabling the signal conducting, and the synapse, which controls signals. Therefore, artificial neural networks are doted of distributed information processing systems,<sup class=\"reference\" id=\"cite_ref-9\"><a href=\"#cite_note-9\">[9]</a></sup> enabling the process and the learning from experiential data. Working like human beings, fault tolerance is also one of the main assets of this principle.<sup class=\"reference\" id=\"cite_ref-Siddique_&amp;_Adeli_1-6\"><a href=\"#cite_note-Siddique_&amp;_Adeli-1\">[1]</a></sup>\n</p><p>Concerning its applications, neural networks can be classified into five groups: data analysis and classification, associative memory, clustering generation of patterns and control.<sup class=\"reference\" id=\"cite_ref-Siddique_&amp;_Adeli_1-7\"><a href=\"#cite_note-Siddique_&amp;_Adeli-1\">[1]</a></sup> Generally, this method aims to analyze and classify medical data, proceed to face and fraud detection, and most importantly deal with nonlinearities of a system in order to control it.<sup class=\"reference\" id=\"cite_ref-10\"><a href=\"#cite_note-10\">[10]</a></sup> Furthermore, neural networks techniques share with the fuzzy logic ones the advantage of enabling <a class=\"mw-redirect\" href=\"/wiki/Data_clustering\" title=\"Data clustering\">data clustering</a>.\n</p>\n<h3><span class=\"mw-headline\" id=\"Evolutionary_computation\">Evolutionary computation</span><span class=\"mw-editsection\"><span class=\"mw-editsection-bracket\">[</span><a href=\"/w/index.php?title=Computational_intelligence&amp;action=edit&amp;section=6\" title=\"Edit section: Evolutionary computation\">edit</a><span class=\"mw-editsection-bracket\">]</span></span></h3>\n<p>Based on the process of <a href=\"/wiki/Evolution\" title=\"Evolution\">natural selection</a> firstly introduced by <a href=\"/wiki/Charles_Darwin\" title=\"Charles Darwin\">Charles Robert Darwin</a>, the evolutionary computation consists in capitalizing on the strength of natural evolution to bring up new artificial evolutionary methodologies.<sup class=\"reference\" id=\"cite_ref-11\"><a href=\"#cite_note-11\">[11]</a></sup><sup class=\"noprint Inline-Template\" style=\"white-space:nowrap;\">[<i><a href=\"/wiki/Wikipedia:Citing_sources\" title=\"Wikipedia:Citing sources\"><span title=\"This citation requires a reference to the specific page or range of pages in which the material appears. (November 2016)\">page needed</span></a></i>]</sup> It also includes other areas such as evolution strategy, and <a href=\"/wiki/Evolutionary_algorithm\" title=\"Evolutionary algorithm\">evolutionary algorithms</a> which are seen as problem solvers... This principle's main applications cover areas such as <a class=\"mw-redirect\" href=\"/wiki/Optimization_(computer_science)\" title=\"Optimization (computer science)\">optimization</a> and <a href=\"/wiki/Multi-objective_optimization\" title=\"Multi-objective optimization\">multi-objective optimization</a>, to which traditional mathematical one techniques aren't enough anymore to apply to a wide range of problems such as <a class=\"mw-redirect\" href=\"/wiki/DNA_Analysis\" title=\"DNA Analysis\">DNA Analysis</a>, scheduling problems...<sup class=\"reference\" id=\"cite_ref-Siddique_&amp;_Adeli_1-8\"><a href=\"#cite_note-Siddique_&amp;_Adeli-1\">[1]</a></sup>\n</p>\n<h3><span class=\"mw-headline\" id=\"Learning_theory\">Learning theory</span><span class=\"mw-editsection\"><span class=\"mw-editsection-bracket\">[</span><a href=\"/w/index.php?title=Computational_intelligence&amp;action=edit&amp;section=7\" title=\"Edit section: Learning theory\">edit</a><span class=\"mw-editsection-bracket\">]</span></span></h3>\n<p>Still looking for a way of \"reasoning\" close to the humans' one, <a href=\"/wiki/Computational_learning_theory\" title=\"Computational learning theory\">learning theory</a> is one of the main approaches of CI. In psychology, learning is the process of bringing together cognitive, emotional and environmental effects and experiences to acquire, enhance or change knowledge, skills, values and world views (Ormrod, 1995; Illeris, 2004).<sup class=\"reference\" id=\"cite_ref-Siddique_&amp;_Adeli_1-9\"><a href=\"#cite_note-Siddique_&amp;_Adeli-1\">[1]</a></sup> Learning theories then helps understanding how these effects and experiences are processed, and then helps making predictions based on previous experience.<sup class=\"reference\" id=\"cite_ref-12\"><a href=\"#cite_note-12\">[12]</a></sup>\n</p>\n<h3><span class=\"mw-headline\" id=\"Probabilistic_methods\">Probabilistic methods</span><span class=\"mw-editsection\"><span class=\"mw-editsection-bracket\">[</span><a href=\"/w/index.php?title=Computational_intelligence&amp;action=edit&amp;section=8\" title=\"Edit section: Probabilistic methods\">edit</a><span class=\"mw-editsection-bracket\">]</span></span></h3>\n<p>Being one of the main elements of fuzzy logic, probabilistic methods firstly introduced by <a href=\"/wiki/Paul_Erd%C5%91s\" title=\"Paul Erdős\">Paul Erdos</a> and <a href=\"/wiki/Joel_Spencer\" title=\"Joel Spencer\">Joel Spencer</a> <sup class=\"reference\" id=\"cite_ref-Siddique_&amp;_Adeli_1-10\"><a href=\"#cite_note-Siddique_&amp;_Adeli-1\">[1]</a></sup>(1974), aim to evaluate the outcomes of a Computation Intelligent system, mostly defined by <a href=\"/wiki/Randomness\" title=\"Randomness\">randomness</a>.<sup class=\"reference\" id=\"cite_ref-13\"><a href=\"#cite_note-13\">[13]</a></sup> Therefore, probabilistic methods bring out the possible solutions to a reasoning problem, based on prior knowledge.\n</p>\n<h2><span class=\"mw-headline\" id=\"See_also\">See also</span><span class=\"mw-editsection\"><span class=\"mw-editsection-bracket\">[</span><a href=\"/w/index.php?title=Computational_intelligence&amp;action=edit&amp;section=9\" title=\"Edit section: See also\">edit</a><span class=\"mw-editsection-bracket\">]</span></span></h2>\n<div aria-label=\"Portals\" class=\"noprint portal plainlist tright\" role=\"navigation\" style=\"margin:0.5em 0 0.5em 1em;border:solid #aaa 1px\">\n<ul style=\"display:table;box-sizing:border-box;padding:0.1em;max-width:175px;background:#f9f9f9;font-size:85%;line-height:110%;font-style:italic;font-weight:bold\">\n<li style=\"display:table-row\"><span style=\"display:table-cell;padding:0.2em;vertical-align:middle;text-align:center\"><a class=\"image\" href=\"/wiki/File:Animation2.gif\"><img alt=\"icon\" class=\"noviewer\" data-file-height=\"78\" data-file-width=\"48\" decoding=\"async\" height=\"28\" src=\"//upload.wikimedia.org/wikipedia/commons/thumb/c/c0/Animation2.gif/17px-Animation2.gif\" srcset=\"//upload.wikimedia.org/wikipedia/commons/thumb/c/c0/Animation2.gif/26px-Animation2.gif 1.5x, //upload.wikimedia.org/wikipedia/commons/thumb/c/c0/Animation2.gif/34px-Animation2.gif 2x\" width=\"17\"/></a></span><span style=\"display:table-cell;padding:0.2em 0.2em 0.2em 0.3em;vertical-align:middle\"><a href=\"/wiki/Portal:Artificial_intelligence\" title=\"Portal:Artificial intelligence\">Artificial intelligence portal</a></span></li></ul></div>\n<div class=\"div-col columns column-width\" style=\"-moz-column-width: 30em; -webkit-column-width: 30em; column-width: 30em;\">\n<ul><li><a href=\"/wiki/Cognitive_robotics\" title=\"Cognitive robotics\">Cognitive robotics</a></li>\n<li><a href=\"/wiki/Computational_finance\" title=\"Computational finance\">Computational finance</a> and <a href=\"/wiki/Computational_economics\" title=\"Computational economics\">Computational economics</a></li>\n<li><a href=\"/wiki/Concept_mining\" title=\"Concept mining\">Concept mining</a></li>\n<li><a href=\"/wiki/Developmental_robotics\" title=\"Developmental robotics\">Developmental robotics</a></li>\n<li><a href=\"/wiki/Data_mining\" title=\"Data mining\">Data mining</a></li>\n<li><a href=\"/wiki/Evolutionary_robotics\" title=\"Evolutionary robotics\">Evolutionary robotics</a></li>\n<li><a href=\"/wiki/Knowledge-based_engineering\" title=\"Knowledge-based engineering\">Knowledge-based engineering</a></li>\n<li><a href=\"/wiki/Natural_computing\" title=\"Natural computing\">Natural computing</a></li>\n<li><a class=\"mw-redirect\" href=\"/wiki/International_Meeting_on_Computational_Intelligence_Methods_for_Bioinformatics_and_Biostatistics\" title=\"International Meeting on Computational Intelligence Methods for Bioinformatics and Biostatistics\">International Meeting on Computational Intelligence Methods for Bioinformatics and Biostatistics</a></li></ul></div>\n<h2><span class=\"mw-headline\" id=\"Notes\">Notes</span><span class=\"mw-editsection\"><span class=\"mw-editsection-bracket\">[</span><a href=\"/w/index.php?title=Computational_intelligence&amp;action=edit&amp;section=10\" title=\"Edit section: Notes\">edit</a><span class=\"mw-editsection-bracket\">]</span></span></h2>\n<ul><li><i><a class=\"external text\" href=\"http://ci.cs.up.ac.za\" rel=\"nofollow\">Computational Intelligence: An Introduction</a></i> by Andries Engelbrecht. Wiley &amp; Sons. <style data-mw-deduplicate=\"TemplateStyles:r879151008\">.mw-parser-output cite.citation{font-style:inherit}.mw-parser-output .citation q{quotes:\"\\\"\"\"\\\"\"\"'\"\"'\"}.mw-parser-output .citation .cs1-lock-free a{background:url(\"//upload.wikimedia.org/wikipedia/commons/thumb/6/65/Lock-green.svg/9px-Lock-green.svg.png\")no-repeat;background-position:right .1em center}.mw-parser-output .citation .cs1-lock-limited a,.mw-parser-output .citation .cs1-lock-registration a{background:url(\"//upload.wikimedia.org/wikipedia/commons/thumb/d/d6/Lock-gray-alt-2.svg/9px-Lock-gray-alt-2.svg.png\")no-repeat;background-position:right .1em center}.mw-parser-output .citation .cs1-lock-subscription a{background:url(\"//upload.wikimedia.org/wikipedia/commons/thumb/a/aa/Lock-red-alt-2.svg/9px-Lock-red-alt-2.svg.png\")no-repeat;background-position:right .1em center}.mw-parser-output .cs1-subscription,.mw-parser-output .cs1-registration{color:#555}.mw-parser-output .cs1-subscription span,.mw-parser-output .cs1-registration span{border-bottom:1px dotted;cursor:help}.mw-parser-output .cs1-ws-icon a{background:url(\"//upload.wikimedia.org/wikipedia/commons/thumb/4/4c/Wikisource-logo.svg/12px-Wikisource-logo.svg.png\")no-repeat;background-position:right .1em center}.mw-parser-output code.cs1-code{color:inherit;background:inherit;border:inherit;padding:inherit}.mw-parser-output .cs1-hidden-error{display:none;font-size:100%}.mw-parser-output .cs1-visible-error{font-size:100%}.mw-parser-output .cs1-maint{display:none;color:#33aa33;margin-left:0.3em}.mw-parser-output .cs1-subscription,.mw-parser-output .cs1-registration,.mw-parser-output .cs1-format{font-size:95%}.mw-parser-output .cs1-kern-left,.mw-parser-output .cs1-kern-wl-left{padding-left:0.2em}.mw-parser-output .cs1-kern-right,.mw-parser-output .cs1-kern-wl-right{padding-right:0.2em}</style><a href=\"/wiki/International_Standard_Book_Number\" title=\"International Standard Book Number\">ISBN</a> <a href=\"/wiki/Special:BookSources/0-470-84870-7\" title=\"Special:BookSources/0-470-84870-7\">0-470-84870-7</a></li>\n<li><i><a class=\"external text\" href=\"http://www.cs.ubc.ca/~poole/ci.html\" rel=\"nofollow\">Computational Intelligence: A Logical Approach</a></i> by David Poole, Alan Mackworth, Randy Goebel. Oxford University Press. <link href=\"mw-data:TemplateStyles:r879151008\" rel=\"mw-deduplicated-inline-style\"/><a href=\"/wiki/International_Standard_Book_Number\" title=\"International Standard Book Number\">ISBN</a> <a href=\"/wiki/Special:BookSources/0-19-510270-3\" title=\"Special:BookSources/0-19-510270-3\">0-19-510270-3</a></li>\n<li><i>Computational Intelligence: A Methodological Introduction</i> by Kruse, Borgelt, Klawonn, Moewes, Steinbrecher, Held, 2013, Springer, <link href=\"mw-data:TemplateStyles:r879151008\" rel=\"mw-deduplicated-inline-style\"/><a href=\"/wiki/International_Standard_Book_Number\" title=\"International Standard Book Number\">ISBN</a> <a href=\"/wiki/Special:BookSources/9781447150121\" title=\"Special:BookSources/9781447150121\">9781447150121</a></li></ul>\n<h2><span class=\"mw-headline\" id=\"Publications\">Publications</span><span class=\"mw-editsection\"><span class=\"mw-editsection-bracket\">[</span><a href=\"/w/index.php?title=Computational_intelligence&amp;action=edit&amp;section=11\" title=\"Edit section: Publications\">edit</a><span class=\"mw-editsection-bracket\">]</span></span></h2>\n<ul><li><a href=\"/wiki/IEEE_Transactions_on_Neural_Networks_and_Learning_Systems\" title=\"IEEE Transactions on Neural Networks and Learning Systems\">IEEE Transactions on Neural Networks and Learning Systems</a></li>\n<li><a href=\"/wiki/IEEE_Transactions_on_Fuzzy_Systems\" title=\"IEEE Transactions on Fuzzy Systems\">IEEE Transactions on Fuzzy Systems</a></li>\n<li><a href=\"/wiki/IEEE_Transactions_on_Evolutionary_Computation\" title=\"IEEE Transactions on Evolutionary Computation\">IEEE Transactions on Evolutionary Computation</a></li>\n<li><a class=\"new\" href=\"/w/index.php?title=IEEE_Transactions_on_Emerging_Topics_in_Computational_Intelligence&amp;action=edit&amp;redlink=1\" title=\"IEEE Transactions on Emerging Topics in Computational Intelligence (page does not exist)\">IEEE Transactions on Emerging Topics in Computational Intelligence</a></li>\n<li><a class=\"new\" href=\"/w/index.php?title=IEEE_Transactions_on_Autonomous_Mental_Development&amp;action=edit&amp;redlink=1\" title=\"IEEE Transactions on Autonomous Mental Development (page does not exist)\">IEEE Transactions on Autonomous Mental Development</a></li>\n<li><a href=\"/wiki/IEEE/ACM_Transactions_on_Computational_Biology_and_Bioinformatics\" title=\"IEEE/ACM Transactions on Computational Biology and Bioinformatics\">IEEE/ACM Transactions on Computational Biology and Bioinformatics</a></li>\n<li><a class=\"new\" href=\"/w/index.php?title=IEEE_Transactions_on_Computational_Intelligence_and_AI_in_Games&amp;action=edit&amp;redlink=1\" title=\"IEEE Transactions on Computational Intelligence and AI in Games (page does not exist)\">IEEE Transactions on Computational Intelligence and AI in Games</a></li>\n<li><a class=\"mw-redirect\" href=\"/wiki/IEEE_Transactions_on_NanoBioscience\" title=\"IEEE Transactions on NanoBioscience\">IEEE Transactions on NanoBioscience</a></li>\n<li><a href=\"/wiki/IEEE_Transactions_on_Information_Forensics_and_Security\" title=\"IEEE Transactions on Information Forensics and Security\">IEEE Transactions on Information Forensics and Security</a></li>\n<li><a class=\"new\" href=\"/w/index.php?title=IEEE_Transactions_on_Affective_Computing&amp;action=edit&amp;redlink=1\" title=\"IEEE Transactions on Affective Computing (page does not exist)\">IEEE Transactions on Affective Computing</a></li>\n<li><a class=\"new\" href=\"/w/index.php?title=IEEE_Transactions_on_Smart_Grid&amp;action=edit&amp;redlink=1\" title=\"IEEE Transactions on Smart Grid (page does not exist)\">IEEE Transactions on Smart Grid</a></li>\n<li><a class=\"new\" href=\"/w/index.php?title=IEEE_Transactions_on_Nanotechnology&amp;action=edit&amp;redlink=1\" title=\"IEEE Transactions on Nanotechnology (page does not exist)\">IEEE Transactions on Nanotechnology</a></li>\n<li><a class=\"new\" href=\"/w/index.php?title=IEEE_Systems_Journal&amp;action=edit&amp;redlink=1\" title=\"IEEE Systems Journal (page does not exist)\">IEEE Systems Journal</a></li></ul>\n<h2><span class=\"mw-headline\" id=\"References\">References</span><span class=\"mw-editsection\"><span class=\"mw-editsection-bracket\">[</span><a href=\"/w/index.php?title=Computational_intelligence&amp;action=edit&amp;section=12\" title=\"Edit section: References\">edit</a><span class=\"mw-editsection-bracket\">]</span></span></h2>\n<div class=\"reflist\" style=\"list-style-type: decimal;\">\n<div class=\"mw-references-wrap mw-references-columns\"><ol class=\"references\">\n<li id=\"cite_note-Siddique_&amp;_Adeli-1\"><span class=\"mw-cite-backlink\">^ <a href=\"#cite_ref-Siddique_&amp;_Adeli_1-0\"><sup><i><b>a</b></i></sup></a> <a href=\"#cite_ref-Siddique_&amp;_Adeli_1-1\"><sup><i><b>b</b></i></sup></a> <a href=\"#cite_ref-Siddique_&amp;_Adeli_1-2\"><sup><i><b>c</b></i></sup></a> <a href=\"#cite_ref-Siddique_&amp;_Adeli_1-3\"><sup><i><b>d</b></i></sup></a> <a href=\"#cite_ref-Siddique_&amp;_Adeli_1-4\"><sup><i><b>e</b></i></sup></a> <a href=\"#cite_ref-Siddique_&amp;_Adeli_1-5\"><sup><i><b>f</b></i></sup></a> <a href=\"#cite_ref-Siddique_&amp;_Adeli_1-6\"><sup><i><b>g</b></i></sup></a> <a href=\"#cite_ref-Siddique_&amp;_Adeli_1-7\"><sup><i><b>h</b></i></sup></a> <a href=\"#cite_ref-Siddique_&amp;_Adeli_1-8\"><sup><i><b>i</b></i></sup></a> <a href=\"#cite_ref-Siddique_&amp;_Adeli_1-9\"><sup><i><b>j</b></i></sup></a> <a href=\"#cite_ref-Siddique_&amp;_Adeli_1-10\"><sup><i><b>k</b></i></sup></a></span> <span class=\"reference-text\"><cite class=\"citation book\">Siddique, Nazmul; Adeli, Hojjat (2013). <i>Computational Intelligence: Synergies of Fuzzy Logic, Neural Networks and Evolutionary Computing</i>. John Wiley &amp; Sons. <a href=\"/wiki/International_Standard_Book_Number\" title=\"International Standard Book Number\">ISBN</a> <a href=\"/wiki/Special:BookSources/978-1-118-53481-6\" title=\"Special:BookSources/978-1-118-53481-6\">978-1-118-53481-6</a>.</cite><span class=\"Z3988\" title=\"ctx_ver=Z39.88-2004&amp;rft_val_fmt=info%3Aofi%2Ffmt%3Akev%3Amtx%3Abook&amp;rft.genre=book&amp;rft.btitle=Computational+Intelligence%3A+Synergies+of+Fuzzy+Logic%2C+Neural+Networks+and+Evolutionary+Computing&amp;rft.pub=John+Wiley+%26+Sons&amp;rft.date=2013&amp;rft.isbn=978-1-118-53481-6&amp;rft.aulast=Siddique&amp;rft.aufirst=Nazmul&amp;rft.au=Adeli%2C+Hojjat&amp;rfr_id=info%3Asid%2Fen.wikipedia.org%3AComputational+intelligence\"></span><link href=\"mw-data:TemplateStyles:r879151008\" rel=\"mw-deduplicated-inline-style\"/></span>\n</li>\n<li id=\"cite_note-2\"><span class=\"mw-cite-backlink\"><b><a href=\"#cite_ref-2\">^</a></b></span> <span class=\"reference-text\"><cite class=\"citation book\">Rutkowski, Leszek (2008). <i>Computational Intelligence: Methods and Techniques</i>. Springer. <a href=\"/wiki/International_Standard_Book_Number\" title=\"International Standard Book Number\">ISBN</a> <a href=\"/wiki/Special:BookSources/978-3-540-76288-1\" title=\"Special:BookSources/978-3-540-76288-1\">978-3-540-76288-1</a>.</cite><span class=\"Z3988\" title=\"ctx_ver=Z39.88-2004&amp;rft_val_fmt=info%3Aofi%2Ffmt%3Akev%3Amtx%3Abook&amp;rft.genre=book&amp;rft.btitle=Computational+Intelligence%3A+Methods+and+Techniques&amp;rft.pub=Springer&amp;rft.date=2008&amp;rft.isbn=978-3-540-76288-1&amp;rft.aulast=Rutkowski&amp;rft.aufirst=Leszek&amp;rfr_id=info%3Asid%2Fen.wikipedia.org%3AComputational+intelligence\"></span><link href=\"mw-data:TemplateStyles:r879151008\" rel=\"mw-deduplicated-inline-style\"/></span>\n</li>\n<li id=\"cite_note-Fuzzy_Logic-3\"><span class=\"mw-cite-backlink\">^ <a href=\"#cite_ref-Fuzzy_Logic_3-0\"><sup><i><b>a</b></i></sup></a> <a href=\"#cite_ref-Fuzzy_Logic_3-1\"><sup><i><b>b</b></i></sup></a></span> <span class=\"reference-text\"><cite class=\"citation web\"><a class=\"external text\" href=\"http://whatis.techtarget.com/definition/fuzzy-logic\" rel=\"nofollow\">\"Fuzzy Logic\"</a>. <i>WhatIs.com</i>. Margaret Rouse. July 2006.</cite><span class=\"Z3988\" title=\"ctx_ver=Z39.88-2004&amp;rft_val_fmt=info%3Aofi%2Ffmt%3Akev%3Amtx%3Ajournal&amp;rft.genre=unknown&amp;rft.jtitle=WhatIs.com&amp;rft.atitle=Fuzzy+Logic&amp;rft.date=2006-07&amp;rft_id=http%3A%2F%2Fwhatis.techtarget.com%2Fdefinition%2Ffuzzy-logic&amp;rfr_id=info%3Asid%2Fen.wikipedia.org%3AComputational+intelligence\"></span><link href=\"mw-data:TemplateStyles:r879151008\" rel=\"mw-deduplicated-inline-style\"/></span>\n</li>\n<li id=\"cite_note-4\"><span class=\"mw-cite-backlink\"><b><a href=\"#cite_ref-4\">^</a></b></span> <span class=\"reference-text\">Beni, G., Wang, J. Swarm Intelligence in Cellular Robotic Systems, Proceed. NATO Advanced Workshop on Robots and Biological Systems, Tuscany, Italy, June 26–30 (1989)</span>\n</li>\n<li id=\"cite_note-5\"><span class=\"mw-cite-backlink\"><b><a href=\"#cite_ref-5\">^</a></b></span> <span class=\"reference-text\"><cite class=\"citation web\"><a class=\"external text\" href=\"http://ethw.org/IEEE_Computational_Intelligence_Society_History\" rel=\"nofollow\">\"IEEE Computational Intelligence Society History\"</a>. <i>Engineering and Technology history Wiki</i>. July 22, 2014<span class=\"reference-accessdate\">. Retrieved <span class=\"nowrap\">2015-10-30</span></span>.</cite><span class=\"Z3988\" title=\"ctx_ver=Z39.88-2004&amp;rft_val_fmt=info%3Aofi%2Ffmt%3Akev%3Amtx%3Ajournal&amp;rft.genre=unknown&amp;rft.jtitle=Engineering+and+Technology+history+Wiki&amp;rft.atitle=IEEE+Computational+Intelligence+Society+History&amp;rft.date=2014-07-22&amp;rft_id=http%3A%2F%2Fethw.org%2FIEEE_Computational_Intelligence_Society_History&amp;rfr_id=info%3Asid%2Fen.wikipedia.org%3AComputational+intelligence\"></span><link href=\"mw-data:TemplateStyles:r879151008\" rel=\"mw-deduplicated-inline-style\"/></span>\n</li>\n<li id=\"cite_note-6\"><span class=\"mw-cite-backlink\"><b><a href=\"#cite_ref-6\">^</a></b></span> <span class=\"reference-text\"><cite class=\"citation web\"><a class=\"external text\" href=\"http://www.andata.at/en/answer/artificial-intelligence-computational-intelligence-softcomputing-natural-computation-whats-the-difference.html\" rel=\"nofollow\">\"Artificial Intelligence, Computational Intelligence, SoftComputing, Natural Computation - what's the difference? - ANDATA\"</a>. <i>www.andata.at</i><span class=\"reference-accessdate\">. Retrieved <span class=\"nowrap\">2015-11-05</span></span>.</cite><span class=\"Z3988\" title=\"ctx_ver=Z39.88-2004&amp;rft_val_fmt=info%3Aofi%2Ffmt%3Akev%3Amtx%3Ajournal&amp;rft.genre=unknown&amp;rft.jtitle=www.andata.at&amp;rft.atitle=Artificial+Intelligence%2C+Computational+Intelligence%2C+SoftComputing%2C+Natural+Computation+-+what%27s+the+difference%3F+-+ANDATA&amp;rft_id=http%3A%2F%2Fwww.andata.at%2Fen%2Fanswer%2Fartificial-intelligence-computational-intelligence-softcomputing-natural-computation-whats-the-difference.html&amp;rfr_id=info%3Asid%2Fen.wikipedia.org%3AComputational+intelligence\"></span><link href=\"mw-data:TemplateStyles:r879151008\" rel=\"mw-deduplicated-inline-style\"/></span>\n</li>\n<li id=\"cite_note-7\"><span class=\"mw-cite-backlink\"><b><a href=\"#cite_ref-7\">^</a></b></span> <span class=\"reference-text\"><cite class=\"citation web\"><a class=\"external text\" href=\"http://www.cs.princeton.edu/courses/archive/fall07/cos436/HIDDEN/Knapp/fuzzy002.htm\" rel=\"nofollow\">\"Fuzzy Sets and Pattern Recognition\"</a>. <i>www.cs.princeton.edu</i><span class=\"reference-accessdate\">. Retrieved <span class=\"nowrap\">2015-11-05</span></span>.</cite><span class=\"Z3988\" title=\"ctx_ver=Z39.88-2004&amp;rft_val_fmt=info%3Aofi%2Ffmt%3Akev%3Amtx%3Ajournal&amp;rft.genre=unknown&amp;rft.jtitle=www.cs.princeton.edu&amp;rft.atitle=Fuzzy+Sets+and+Pattern+Recognition&amp;rft_id=http%3A%2F%2Fwww.cs.princeton.edu%2Fcourses%2Farchive%2Ffall07%2Fcos436%2FHIDDEN%2FKnapp%2Ffuzzy002.htm&amp;rfr_id=info%3Asid%2Fen.wikipedia.org%3AComputational+intelligence\"></span><link href=\"mw-data:TemplateStyles:r879151008\" rel=\"mw-deduplicated-inline-style\"/></span>\n</li>\n<li id=\"cite_note-8\"><span class=\"mw-cite-backlink\"><b><a href=\"#cite_ref-8\">^</a></b></span> <span class=\"reference-text\">R. Pfeifer. 2013. Chapter 5: FUZZY Logic. Lecture notes on \"Real-world computing\". Zurich. University of Zurich.</span>\n</li>\n<li id=\"cite_note-9\"><span class=\"mw-cite-backlink\"><b><a href=\"#cite_ref-9\">^</a></b></span> <span class=\"reference-text\"><cite class=\"citation journal\">Stergiou, Christos; Siganos, Dimitrios. <a class=\"external text\" href=\"http://www.doc.ic.ac.uk/~nd/surprise_96/journal/vol4/cs11/report.html\" rel=\"nofollow\">\"Neural Networks\"</a>. <i>SURPRISE 96 Journal</i>. <a href=\"/wiki/Imperial_College_London\" title=\"Imperial College London\">Imperial College London</a><span class=\"reference-accessdate\">. Retrieved <span class=\"nowrap\">March 11,</span> 2015</span>.</cite><span class=\"Z3988\" title=\"ctx_ver=Z39.88-2004&amp;rft_val_fmt=info%3Aofi%2Ffmt%3Akev%3Amtx%3Ajournal&amp;rft.genre=article&amp;rft.jtitle=SURPRISE+96+Journal&amp;rft.atitle=Neural+Networks&amp;rft.aulast=Stergiou&amp;rft.aufirst=Christos&amp;rft.au=Siganos%2C+Dimitrios&amp;rft_id=http%3A%2F%2Fwww.doc.ic.ac.uk%2F~nd%2Fsurprise_96%2Fjournal%2Fvol4%2Fcs11%2Freport.html&amp;rfr_id=info%3Asid%2Fen.wikipedia.org%3AComputational+intelligence\"></span><link href=\"mw-data:TemplateStyles:r879151008\" rel=\"mw-deduplicated-inline-style\"/></span>\n</li>\n<li id=\"cite_note-10\"><span class=\"mw-cite-backlink\"><b><a href=\"#cite_ref-10\">^</a></b></span> <span class=\"reference-text\"><cite class=\"citation journal\">Somers, Mark John; Casal, Jose C. (July 2009). <a class=\"external text\" href=\"http://leeds-faculty.colorado.edu/dahe7472/Organizational%20Research%20Methods-2009-Somers-403-17.pdf\" rel=\"nofollow\">\"Using Artificial Neural Networks to Model Nonlinearity\"</a> <span class=\"cs1-format\">(PDF)</span>. <i>Organizational Research Methods</i>. <b>12</b> (3). <a href=\"/wiki/Digital_object_identifier\" title=\"Digital object identifier\">doi</a>:<a class=\"external text\" href=\"//doi.org/10.1177%2F1094428107309326\" rel=\"nofollow\">10.1177/1094428107309326</a><span class=\"reference-accessdate\">. Retrieved <span class=\"nowrap\">2015-10-31</span></span>.</cite><span class=\"Z3988\" title=\"ctx_ver=Z39.88-2004&amp;rft_val_fmt=info%3Aofi%2Ffmt%3Akev%3Amtx%3Ajournal&amp;rft.genre=article&amp;rft.jtitle=Organizational+Research+Methods&amp;rft.atitle=Using+Artificial+Neural+Networks+to+Model+Nonlinearity&amp;rft.volume=12&amp;rft.issue=3&amp;rft.date=2009-07&amp;rft_id=info%3Adoi%2F10.1177%2F1094428107309326&amp;rft.aulast=Somers&amp;rft.aufirst=Mark+John&amp;rft.au=Casal%2C+Jose+C.&amp;rft_id=http%3A%2F%2Fleeds-faculty.colorado.edu%2Fdahe7472%2FOrganizational%2520Research%2520Methods-2009-Somers-403-17.pdf&amp;rfr_id=info%3Asid%2Fen.wikipedia.org%3AComputational+intelligence\"></span><link href=\"mw-data:TemplateStyles:r879151008\" rel=\"mw-deduplicated-inline-style\"/></span>\n</li>\n<li id=\"cite_note-11\"><span class=\"mw-cite-backlink\"><b><a href=\"#cite_ref-11\">^</a></b></span> <span class=\"reference-text\"><cite class=\"citation book\">De Jong, K. (2006). <i>Evolutionary Computation:A Unified Approach</i>. MIT Press. <a href=\"/wiki/International_Standard_Book_Number\" title=\"International Standard Book Number\">ISBN</a> <a href=\"/wiki/Special:BookSources/9780262041942\" title=\"Special:BookSources/9780262041942\">9780262041942</a>.</cite><span class=\"Z3988\" title=\"ctx_ver=Z39.88-2004&amp;rft_val_fmt=info%3Aofi%2Ffmt%3Akev%3Amtx%3Abook&amp;rft.genre=book&amp;rft.btitle=Evolutionary+Computation%3AA+Unified+Approach&amp;rft.pub=MIT+Press&amp;rft.date=2006&amp;rft.isbn=9780262041942&amp;rft.aulast=De+Jong&amp;rft.aufirst=K.&amp;rfr_id=info%3Asid%2Fen.wikipedia.org%3AComputational+intelligence\"></span><link href=\"mw-data:TemplateStyles:r879151008\" rel=\"mw-deduplicated-inline-style\"/></span>\n</li>\n<li id=\"cite_note-12\"><span class=\"mw-cite-backlink\"><b><a href=\"#cite_ref-12\">^</a></b></span> <span class=\"reference-text\"><cite class=\"citation web\">Worrell, James. <a class=\"external text\" href=\"https://www.cs.ox.ac.uk/teaching/courses/2014-2015/clt/\" rel=\"nofollow\">\"Computational Learning Theory: 2014-2015\"</a>. <i>University of Oxford</i>. Presentation page of CLT course. University of Oxford<span class=\"reference-accessdate\">. Retrieved <span class=\"nowrap\">February 11,</span> 2015</span>.</cite><span class=\"Z3988\" title=\"ctx_ver=Z39.88-2004&amp;rft_val_fmt=info%3Aofi%2Ffmt%3Akev%3Amtx%3Ajournal&amp;rft.genre=unknown&amp;rft.jtitle=University+of+Oxford&amp;rft.atitle=Computational+Learning+Theory%3A+2014-2015&amp;rft.aulast=Worrell&amp;rft.aufirst=James&amp;rft_id=https%3A%2F%2Fwww.cs.ox.ac.uk%2Fteaching%2Fcourses%2F2014-2015%2Fclt%2F&amp;rfr_id=info%3Asid%2Fen.wikipedia.org%3AComputational+intelligence\"></span><link href=\"mw-data:TemplateStyles:r879151008\" rel=\"mw-deduplicated-inline-style\"/></span>\n</li>\n<li id=\"cite_note-13\"><span class=\"mw-cite-backlink\"><b><a href=\"#cite_ref-13\">^</a></b></span> <span class=\"reference-text\"><cite class=\"citation book\">Palit, Ajoy K.; Popovic, Dobrivoje (2006). <i>Computational Intelligence in Time Series Forecasting : Theory and Engineering Applications</i>. Springer Science &amp; Business Media. p. 4. <a href=\"/wiki/International_Standard_Book_Number\" title=\"International Standard Book Number\">ISBN</a> <a href=\"/wiki/Special:BookSources/9781846281846\" title=\"Special:BookSources/9781846281846\">9781846281846</a>.</cite><span class=\"Z3988\" title=\"ctx_ver=Z39.88-2004&amp;rft_val_fmt=info%3Aofi%2Ffmt%3Akev%3Amtx%3Abook&amp;rft.genre=book&amp;rft.btitle=Computational+Intelligence+in+Time+Series+Forecasting+%3A+Theory+and+Engineering+Applications&amp;rft.pages=4&amp;rft.pub=Springer+Science+%26+Business+Media&amp;rft.date=2006&amp;rft.isbn=9781846281846&amp;rft.aulast=Palit&amp;rft.aufirst=Ajoy+K.&amp;rft.au=Popovic%2C+Dobrivoje&amp;rfr_id=info%3Asid%2Fen.wikipedia.org%3AComputational+intelligence\"></span><link href=\"mw-data:TemplateStyles:r879151008\" rel=\"mw-deduplicated-inline-style\"/></span>\n</li>\n</ol></div></div>\n<!-- \nNewPP limit report\nParsed by mw1239\nCached time: 20190224203544\nCache expiry: 2073600\nDynamic content: false\nCPU time usage: 0.432 seconds\nReal time usage: 0.577 seconds\nPreprocessor visited node count: 2764/1000000\nPreprocessor generated node count: 0/1500000\nPost‐expand include size: 48712/2097152 bytes\nTemplate argument size: 8164/2097152 bytes\nHighest expansion depth: 12/40\nExpensive parser function count: 10/500\nUnstrip recursion depth: 1/20\nUnstrip post‐expand size: 41243/5000000 bytes\nNumber of Wikibase entities loaded: 1/400\nLua time usage: 0.193/10.000 seconds\nLua memory usage: 4.35 MB/50 MB\n-->\n<!--\nTransclusion expansion time report (%,ms,calls,template)\n100.00%  501.349      1 -total\n 27.80%  139.389      1 Template:Reflist\n 18.18%   91.161      8 Template:Fix\n 17.77%   89.069      3 Template:ISBN\n 12.49%   62.630      4 Template:Cite_book\n 11.82%   59.271      8 Template:Delink\n 11.01%   55.183      3 Template:Page_needed\n 10.48%   52.541      1 Template:More_footnotes\n 10.44%   52.344      3 Template:Catalog_lookup_link\n  8.43%   42.280      1 Template:Ambox\n-->\n<!-- Saved in parser cache with key enwiki:pcache:idhash:1563306-0!canonical and timestamp 20190224203543 and revision id 865907791\n -->\n</div><noscript><img alt=\"\" height=\"1\" src=\"//en.wikipedia.org/wiki/Special:CentralAutoLogin/start?type=1x1\" style=\"border: none; position: absolute;\" title=\"\" width=\"1\"/></noscript></div> <div class=\"printfooter\">\n\t\t\t\t\t\tRetrieved from \"<a dir=\"ltr\" href=\"https://en.wikipedia.org/w/index.php?title=Computational_intelligence&amp;oldid=865907791\">https://en.wikipedia.org/w/index.php?title=Computational_intelligence&amp;oldid=865907791</a>\"\t\t\t\t\t</div>\n<div class=\"catlinks\" data-mw=\"interface\" id=\"catlinks\"><div class=\"mw-normal-catlinks\" id=\"mw-normal-catlinks\"><a href=\"/wiki/Help:Category\" title=\"Help:Category\">Categories</a>: <ul><li><a href=\"/wiki/Category:Artificial_intelligence\" title=\"Category:Artificial intelligence\">Artificial intelligence</a></li></ul></div><div class=\"mw-hidden-catlinks mw-hidden-cats-hidden\" id=\"mw-hidden-catlinks\">Hidden categories: <ul><li><a href=\"/wiki/Category:Use_mdy_dates_from_October_2016\" title=\"Category:Use mdy dates from October 2016\">Use mdy dates from October 2016</a></li><li><a href=\"/wiki/Category:Use_American_English_from_October_2016\" title=\"Category:Use American English from October 2016\">Use American English from October 2016</a></li><li><a href=\"/wiki/Category:All_Wikipedia_articles_written_in_American_English\" title=\"Category:All Wikipedia articles written in American English\">All Wikipedia articles written in American English</a></li><li><a href=\"/wiki/Category:Articles_lacking_in-text_citations_from_July_2012\" title=\"Category:Articles lacking in-text citations from July 2012\">Articles lacking in-text citations from July 2012</a></li><li><a href=\"/wiki/Category:All_articles_lacking_in-text_citations\" title=\"Category:All articles lacking in-text citations\">All articles lacking in-text citations</a></li><li><a href=\"/wiki/Category:Wikipedia_articles_needing_page_number_citations_from_November_2016\" title=\"Category:Wikipedia articles needing page number citations from November 2016\">Wikipedia articles needing page number citations from November 2016</a></li><li><a href=\"/wiki/Category:All_articles_with_specifically_marked_weasel-worded_phrases\" title=\"Category:All articles with specifically marked weasel-worded phrases\">All articles with specifically marked weasel-worded phrases</a></li><li><a href=\"/wiki/Category:Articles_with_specifically_marked_weasel-worded_phrases_from_October_2017\" title=\"Category:Articles with specifically marked weasel-worded phrases from October 2017\">Articles with specifically marked weasel-worded phrases from October 2017</a></li><li><a href=\"/wiki/Category:All_articles_with_unsourced_statements\" title=\"Category:All articles with unsourced statements\">All articles with unsourced statements</a></li><li><a href=\"/wiki/Category:Articles_with_unsourced_statements_from_October_2017\" title=\"Category:Articles with unsourced statements from October 2017\">Articles with unsourced statements from October 2017</a></li><li><a href=\"/wiki/Category:Wikipedia_articles_needing_clarification_from_October_2017\" title=\"Category:Wikipedia articles needing clarification from October 2017\">Wikipedia articles needing clarification from October 2017</a></li><li><a href=\"/wiki/Category:Articles_with_unsourced_statements_from_November_2016\" title=\"Category:Articles with unsourced statements from November 2016\">Articles with unsourced statements from November 2016</a></li></ul></div></div> <div class=\"visualClear\"></div>\n</div>\n</div>\n<div id=\"mw-navigation\">\n<h2>Navigation menu</h2>\n<div id=\"mw-head\">\n<div aria-labelledby=\"p-personal-label\" id=\"p-personal\" role=\"navigation\">\n<h3 id=\"p-personal-label\">Personal tools</h3>\n<ul>\n<li id=\"pt-anonuserpage\">Not logged in</li><li id=\"pt-anontalk\"><a accesskey=\"n\" href=\"/wiki/Special:MyTalk\" title=\"Discussion about edits from this IP address [n]\">Talk</a></li><li id=\"pt-anoncontribs\"><a accesskey=\"y\" href=\"/wiki/Special:MyContributions\" title=\"A list of edits made from this IP address [y]\">Contributions</a></li><li id=\"pt-createaccount\"><a href=\"/w/index.php?title=Special:CreateAccount&amp;returnto=Computational+intelligence\" title=\"You are encouraged to create an account and log in; however, it is not mandatory\">Create account</a></li><li id=\"pt-login\"><a accesskey=\"o\" href=\"/w/index.php?title=Special:UserLogin&amp;returnto=Computational+intelligence\" title=\"You're encouraged to log in; however, it's not mandatory. [o]\">Log in</a></li> </ul>\n</div>\n<div id=\"left-navigation\">\n<div aria-labelledby=\"p-namespaces-label\" class=\"vectorTabs\" id=\"p-namespaces\" role=\"navigation\">\n<h3 id=\"p-namespaces-label\">Namespaces</h3>\n<ul>\n<li class=\"selected\" id=\"ca-nstab-main\"><span><a accesskey=\"c\" href=\"/wiki/Computational_intelligence\" title=\"View the content page [c]\">Article</a></span></li><li id=\"ca-talk\"><span><a accesskey=\"t\" href=\"/wiki/Talk:Computational_intelligence\" rel=\"discussion\" title=\"Discussion about the content page [t]\">Talk</a></span></li> </ul>\n</div>\n<div aria-labelledby=\"p-variants-label\" class=\"vectorMenu emptyPortlet\" id=\"p-variants\" role=\"navigation\">\n<input aria-labelledby=\"p-variants-label\" class=\"vectorMenuCheckbox\" type=\"checkbox\"/>\n<h3 id=\"p-variants-label\">\n<span>Variants</span>\n</h3>\n<ul class=\"menu\">\n</ul>\n</div>\n</div>\n<div id=\"right-navigation\">\n<div aria-labelledby=\"p-views-label\" class=\"vectorTabs\" id=\"p-views\" role=\"navigation\">\n<h3 id=\"p-views-label\">Views</h3>\n<ul>\n<li class=\"collapsible selected\" id=\"ca-view\"><span><a href=\"/wiki/Computational_intelligence\">Read</a></span></li><li class=\"collapsible\" id=\"ca-edit\"><span><a accesskey=\"e\" href=\"/w/index.php?title=Computational_intelligence&amp;action=edit\" title=\"Edit this page [e]\">Edit</a></span></li><li class=\"collapsible\" id=\"ca-history\"><span><a accesskey=\"h\" href=\"/w/index.php?title=Computational_intelligence&amp;action=history\" title=\"Past revisions of this page [h]\">View history</a></span></li> </ul>\n</div>\n<div aria-labelledby=\"p-cactions-label\" class=\"vectorMenu emptyPortlet\" id=\"p-cactions\" role=\"navigation\">\n<input aria-labelledby=\"p-cactions-label\" class=\"vectorMenuCheckbox\" type=\"checkbox\"/>\n<h3 id=\"p-cactions-label\"><span>More</span></h3>\n<ul class=\"menu\">\n</ul>\n</div>\n<div id=\"p-search\" role=\"search\">\n<h3>\n<label for=\"searchInput\">Search</label>\n</h3>\n<form action=\"/w/index.php\" id=\"searchform\">\n<div id=\"simpleSearch\">\n<input accesskey=\"f\" id=\"searchInput\" name=\"search\" placeholder=\"Search Wikipedia\" title=\"Search Wikipedia [f]\" type=\"search\"/><input name=\"title\" type=\"hidden\" value=\"Special:Search\"/><input class=\"searchButton mw-fallbackSearchButton\" id=\"mw-searchButton\" name=\"fulltext\" title=\"Search Wikipedia for this text\" type=\"submit\" value=\"Search\"/><input class=\"searchButton\" id=\"searchButton\" name=\"go\" title=\"Go to a page with this exact name if it exists\" type=\"submit\" value=\"Go\"/> </div>\n</form>\n</div>\n</div>\n</div>\n<div id=\"mw-panel\">\n<div id=\"p-logo\" role=\"banner\"><a class=\"mw-wiki-logo\" href=\"/wiki/Main_Page\" title=\"Visit the main page\"></a></div>\n<div aria-labelledby=\"p-navigation-label\" class=\"portal\" id=\"p-navigation\" role=\"navigation\">\n<h3 id=\"p-navigation-label\">Navigation</h3>\n<div class=\"body\">\n<ul>\n<li id=\"n-mainpage-description\"><a accesskey=\"z\" href=\"/wiki/Main_Page\" title=\"Visit the main page [z]\">Main page</a></li><li id=\"n-contents\"><a href=\"/wiki/Portal:Contents\" title=\"Guides to browsing Wikipedia\">Contents</a></li><li id=\"n-featuredcontent\"><a href=\"/wiki/Portal:Featured_content\" title=\"Featured content – the best of Wikipedia\">Featured content</a></li><li id=\"n-currentevents\"><a href=\"/wiki/Portal:Current_events\" title=\"Find background information on current events\">Current events</a></li><li id=\"n-randompage\"><a accesskey=\"x\" href=\"/wiki/Special:Random\" title=\"Load a random article [x]\">Random article</a></li><li id=\"n-sitesupport\"><a href=\"https://donate.wikimedia.org/wiki/Special:FundraiserRedirector?utm_source=donate&amp;utm_medium=sidebar&amp;utm_campaign=C13_en.wikipedia.org&amp;uselang=en\" title=\"Support us\">Donate to Wikipedia</a></li><li id=\"n-shoplink\"><a href=\"//shop.wikimedia.org\" title=\"Visit the Wikipedia store\">Wikipedia store</a></li> </ul>\n</div>\n</div>\n<div aria-labelledby=\"p-interaction-label\" class=\"portal\" id=\"p-interaction\" role=\"navigation\">\n<h3 id=\"p-interaction-label\">Interaction</h3>\n<div class=\"body\">\n<ul>\n<li id=\"n-help\"><a href=\"/wiki/Help:Contents\" title=\"Guidance on how to use and edit Wikipedia\">Help</a></li><li id=\"n-aboutsite\"><a href=\"/wiki/Wikipedia:About\" title=\"Find out about Wikipedia\">About Wikipedia</a></li><li id=\"n-portal\"><a href=\"/wiki/Wikipedia:Community_portal\" title=\"About the project, what you can do, where to find things\">Community portal</a></li><li id=\"n-recentchanges\"><a accesskey=\"r\" href=\"/wiki/Special:RecentChanges\" title=\"A list of recent changes in the wiki [r]\">Recent changes</a></li><li id=\"n-contactpage\"><a href=\"//en.wikipedia.org/wiki/Wikipedia:Contact_us\" title=\"How to contact Wikipedia\">Contact page</a></li> </ul>\n</div>\n</div>\n<div aria-labelledby=\"p-tb-label\" class=\"portal\" id=\"p-tb\" role=\"navigation\">\n<h3 id=\"p-tb-label\">Tools</h3>\n<div class=\"body\">\n<ul>\n<li id=\"t-whatlinkshere\"><a accesskey=\"j\" href=\"/wiki/Special:WhatLinksHere/Computational_intelligence\" title=\"List of all English Wikipedia pages containing links to this page [j]\">What links here</a></li><li id=\"t-recentchangeslinked\"><a accesskey=\"k\" href=\"/wiki/Special:RecentChangesLinked/Computational_intelligence\" rel=\"nofollow\" title=\"Recent changes in pages linked from this page [k]\">Related changes</a></li><li id=\"t-upload\"><a accesskey=\"u\" href=\"/wiki/Wikipedia:File_Upload_Wizard\" title=\"Upload files [u]\">Upload file</a></li><li id=\"t-specialpages\"><a accesskey=\"q\" href=\"/wiki/Special:SpecialPages\" title=\"A list of all special pages [q]\">Special pages</a></li><li id=\"t-permalink\"><a href=\"/w/index.php?title=Computational_intelligence&amp;oldid=865907791\" title=\"Permanent link to this revision of the page\">Permanent link</a></li><li id=\"t-info\"><a href=\"/w/index.php?title=Computational_intelligence&amp;action=info\" title=\"More information about this page\">Page information</a></li><li id=\"t-wikibase\"><a accesskey=\"g\" href=\"https://www.wikidata.org/wiki/Special:EntityPage/Q1122090\" title=\"Link to connected data repository item [g]\">Wikidata item</a></li><li id=\"t-cite\"><a href=\"/w/index.php?title=Special:CiteThisPage&amp;page=Computational_intelligence&amp;id=865907791\" title=\"Information on how to cite this page\">Cite this page</a></li> </ul>\n</div>\n</div>\n<div aria-labelledby=\"p-coll-print_export-label\" class=\"portal\" id=\"p-coll-print_export\" role=\"navigation\">\n<h3 id=\"p-coll-print_export-label\">Print/export</h3>\n<div class=\"body\">\n<ul>\n<li id=\"coll-create_a_book\"><a href=\"/w/index.php?title=Special:Book&amp;bookcmd=book_creator&amp;referer=Computational+intelligence\">Create a book</a></li><li id=\"coll-download-as-rdf2latex\"><a href=\"/w/index.php?title=Special:ElectronPdf&amp;page=Computational+intelligence&amp;action=show-download-screen\">Download as PDF</a></li><li id=\"t-print\"><a accesskey=\"p\" href=\"/w/index.php?title=Computational_intelligence&amp;printable=yes\" title=\"Printable version of this page [p]\">Printable version</a></li> </ul>\n</div>\n</div>\n<div aria-labelledby=\"p-lang-label\" class=\"portal\" id=\"p-lang\" role=\"navigation\">\n<h3 id=\"p-lang-label\">Languages</h3>\n<div class=\"body\">\n<ul>\n<li class=\"interlanguage-link interwiki-de\"><a class=\"interlanguage-link-target\" href=\"https://de.wikipedia.org/wiki/Computational_Intelligence\" hreflang=\"de\" lang=\"de\" title=\"Computational Intelligence – German\">Deutsch</a></li><li class=\"interlanguage-link interwiki-es\"><a class=\"interlanguage-link-target\" href=\"https://es.wikipedia.org/wiki/Inteligencia_computacional\" hreflang=\"es\" lang=\"es\" title=\"Inteligencia computacional – Spanish\">Español</a></li><li class=\"interlanguage-link interwiki-fa\"><a class=\"interlanguage-link-target\" href=\"https://fa.wikipedia.org/wiki/%D9%87%D9%88%D8%B4_%D9%85%D8%AD%D8%A7%D8%B3%D8%A8%D8%A7%D8%AA%DB%8C\" hreflang=\"fa\" lang=\"fa\" title=\"هوش محاسباتی – Persian\">فارسی</a></li><li class=\"interlanguage-link interwiki-fr\"><a class=\"interlanguage-link-target\" href=\"https://fr.wikipedia.org/wiki/Intelligence_computationnelle\" hreflang=\"fr\" lang=\"fr\" title=\"Intelligence computationnelle – French\">Français</a></li><li class=\"interlanguage-link interwiki-he\"><a class=\"interlanguage-link-target\" href=\"https://he.wikipedia.org/wiki/%D7%91%D7%99%D7%A0%D7%94_%D7%97%D7%99%D7%A9%D7%95%D7%91%D7%99%D7%AA\" hreflang=\"he\" lang=\"he\" title=\"בינה חישובית – Hebrew\">עברית</a></li><li class=\"interlanguage-link interwiki-ja\"><a class=\"interlanguage-link-target\" href=\"https://ja.wikipedia.org/wiki/%E8%A8%88%E7%AE%97%E7%9F%A5%E8%83%BD\" hreflang=\"ja\" lang=\"ja\" title=\"計算知能 – Japanese\">日本語</a></li><li class=\"interlanguage-link interwiki-pl\"><a class=\"interlanguage-link-target\" href=\"https://pl.wikipedia.org/wiki/Obliczenia_inteligentne\" hreflang=\"pl\" lang=\"pl\" title=\"Obliczenia inteligentne – Polish\">Polski</a></li><li class=\"interlanguage-link interwiki-pt\"><a class=\"interlanguage-link-target\" href=\"https://pt.wikipedia.org/wiki/Intelig%C3%AAncia_computacional\" hreflang=\"pt\" lang=\"pt\" title=\"Inteligência computacional – Portuguese\">Português</a></li><li class=\"interlanguage-link interwiki-ru\"><a class=\"interlanguage-link-target\" href=\"https://ru.wikipedia.org/wiki/%D0%92%D1%8B%D1%87%D0%B8%D1%81%D0%BB%D0%B8%D1%82%D0%B5%D0%BB%D1%8C%D0%BD%D1%8B%D0%B9_%D0%B8%D0%BD%D1%82%D0%B5%D0%BB%D0%BB%D0%B5%D0%BA%D1%82\" hreflang=\"ru\" lang=\"ru\" title=\"Вычислительный интеллект – Russian\">Русский</a></li><li class=\"interlanguage-link interwiki-sk\"><a class=\"interlanguage-link-target\" href=\"https://sk.wikipedia.org/wiki/V%C3%BDpo%C4%8Dtov%C3%A1_inteligencia\" hreflang=\"sk\" lang=\"sk\" title=\"Výpočtová inteligencia – Slovak\">Slovenčina</a></li> </ul>\n<div class=\"after-portlet after-portlet-lang\"><span class=\"wb-langlinks-edit wb-langlinks-link\"><a class=\"wbc-editpage\" href=\"https://www.wikidata.org/wiki/Special:EntityPage/Q1122090#sitelinks-wikipedia\" title=\"Edit interlanguage links\">Edit links</a></span></div> </div>\n</div>\n</div>\n</div>\n<div id=\"footer\" role=\"contentinfo\">\n<ul id=\"footer-info\">\n<li id=\"footer-info-lastmod\"> This page was last edited on 26 October 2018, at 23:47<span class=\"anonymous-show\"> (UTC)</span>.</li>\n<li id=\"footer-info-copyright\">Text is available under the <a href=\"//en.wikipedia.org/wiki/Wikipedia:Text_of_Creative_Commons_Attribution-ShareAlike_3.0_Unported_License\" rel=\"license\">Creative Commons Attribution-ShareAlike License</a><a href=\"//creativecommons.org/licenses/by-sa/3.0/\" rel=\"license\" style=\"display:none;\"></a>;\nadditional terms may apply.  By using this site, you agree to the <a href=\"//foundation.wikimedia.org/wiki/Terms_of_Use\">Terms of Use</a> and <a href=\"//foundation.wikimedia.org/wiki/Privacy_policy\">Privacy Policy</a>. Wikipedia® is a registered trademark of the <a href=\"//www.wikimediafoundation.org/\">Wikimedia Foundation, Inc.</a>, a non-profit organization.</li>\n</ul>\n<ul id=\"footer-places\">\n<li id=\"footer-places-privacy\"><a class=\"extiw\" href=\"https://foundation.wikimedia.org/wiki/Privacy_policy\" title=\"wmf:Privacy policy\">Privacy policy</a></li>\n<li id=\"footer-places-about\"><a href=\"/wiki/Wikipedia:About\" title=\"Wikipedia:About\">About Wikipedia</a></li>\n<li id=\"footer-places-disclaimer\"><a href=\"/wiki/Wikipedia:General_disclaimer\" title=\"Wikipedia:General disclaimer\">Disclaimers</a></li>\n<li id=\"footer-places-contact\"><a href=\"//en.wikipedia.org/wiki/Wikipedia:Contact_us\">Contact Wikipedia</a></li>\n<li id=\"footer-places-developers\"><a href=\"https://www.mediawiki.org/wiki/Special:MyLanguage/How_to_contribute\">Developers</a></li>\n<li id=\"footer-places-cookiestatement\"><a href=\"https://foundation.wikimedia.org/wiki/Cookie_statement\">Cookie statement</a></li>\n<li id=\"footer-places-mobileview\"><a class=\"noprint stopMobileRedirectToggle\" href=\"//en.m.wikipedia.org/w/index.php?title=Computational_intelligence&amp;mobileaction=toggle_view_mobile\">Mobile view</a></li>\n</ul>\n<ul class=\"noprint\" id=\"footer-icons\">\n<li id=\"footer-copyrightico\">\n<a href=\"https://wikimediafoundation.org/\"><img alt=\"Wikimedia Foundation\" height=\"31\" src=\"/static/images/wikimedia-button.png\" srcset=\"/static/images/wikimedia-button-1.5x.png 1.5x, /static/images/wikimedia-button-2x.png 2x\" width=\"88\"/></a> </li>\n<li id=\"footer-poweredbyico\">\n<a href=\"//www.mediawiki.org/\"><img alt=\"Powered by MediaWiki\" height=\"31\" src=\"/static/images/poweredby_mediawiki_88x31.png\" srcset=\"/static/images/poweredby_mediawiki_132x47.png 1.5x, /static/images/poweredby_mediawiki_176x62.png 2x\" width=\"88\"/></a> </li>\n</ul>\n<div style=\"clear: both;\"></div>\n</div>\n<script>(window.RLQ=window.RLQ||[]).push(function(){mw.config.set({\"wgPageParseReport\":{\"limitreport\":{\"cputime\":\"0.432\",\"walltime\":\"0.577\",\"ppvisitednodes\":{\"value\":2764,\"limit\":1000000},\"ppgeneratednodes\":{\"value\":0,\"limit\":1500000},\"postexpandincludesize\":{\"value\":48712,\"limit\":2097152},\"templateargumentsize\":{\"value\":8164,\"limit\":2097152},\"expansiondepth\":{\"value\":12,\"limit\":40},\"expensivefunctioncount\":{\"value\":10,\"limit\":500},\"unstrip-depth\":{\"value\":1,\"limit\":20},\"unstrip-size\":{\"value\":41243,\"limit\":5000000},\"entityaccesscount\":{\"value\":1,\"limit\":400},\"timingprofile\":[\"100.00%  501.349      1 -total\",\" 27.80%  139.389      1 Template:Reflist\",\" 18.18%   91.161      8 Template:Fix\",\" 17.77%   89.069      3 Template:ISBN\",\" 12.49%   62.630      4 Template:Cite_book\",\" 11.82%   59.271      8 Template:Delink\",\" 11.01%   55.183      3 Template:Page_needed\",\" 10.48%   52.541      1 Template:More_footnotes\",\" 10.44%   52.344      3 Template:Catalog_lookup_link\",\"  8.43%   42.280      1 Template:Ambox\"]},\"scribunto\":{\"limitreport-timeusage\":{\"value\":\"0.193\",\"limit\":\"10.000\"},\"limitreport-memusage\":{\"value\":4566319,\"limit\":52428800}},\"cachereport\":{\"origin\":\"mw1239\",\"timestamp\":\"20190224203544\",\"ttl\":2073600,\"transientcontent\":false}}});mw.config.set({\"wgBackendResponseTime\":686,\"wgHostname\":\"mw1239\"});});</script>\n</body>\n</html>\n",
  "table_of_contents": [
    "1 History[5]",
    "2 Difference between Computational and Artificial Intelligence",
    "3 The five main principles of CI and its applications",
    "3.1 Fuzzy logic",
    "3.2 Neural networks",
    "3.3 Evolutionary computation",
    "3.4 Learning theory",
    "3.5 Probabilistic methods",
    "4 See also",
    "5 Notes",
    "6 Publications",
    "7 References"
  ],
  "graphics": [],
  "paragraphs": [
    {
      "title": "",
      "text": "\n\nThe expression computational intelligence (CI) usually refers to the ability of a computer to learn a specific task from data or experimental observation. Even though it is commonly considered a synonym of soft computing, there is still no commonly accepted definition of computational intelligence.\n\nGenerally, computational intelligence is a set of nature-inspired computational methodologies and approaches to address complex real-world problems to which mathematical or traditional modelling can be useless for a few reasons: the processes might be too complex for mathematical reasoning, it might contain some uncertainties during the process, or the process might simply be stochastic in nature.[1][page needed] Indeed, many real-life problems cannot be translated into binary language (unique values of 0 and 1) for computers to process it. Computational Intelligence therefore provides solutions for such problems.\n\nThe methods used are close to the human's way of reasoning, i.e. it uses inexact and incomplete knowledge, and it is able to produce control actions in an adaptive way. CI therefore uses a combination of five main complementary techniques.[1] The fuzzy logic which enables the computer to understand natural language,[2][page needed][3] artificial neural networks which permits the system to learn experiential data by operating like the biological one, evolutionary computing, which is based on the process of natural selection, learning theory, and probabilistic methods which helps dealing with uncertainty imprecision.[1]\n\nExcept those main principles, currently popular approaches include biologically inspired algorithms such as swarm intelligence[4] and artificial immune systems, which can be seen as a part of evolutionary computation, image processing, data mining, natural language processing, and artificial intelligence, which tends to be confused with Computational Intelligence. But although both Computational Intelligence (CI) and Artificial Intelligence (AI) seek similar goals, there's a clear distinction between them[according to whom?][citation needed].\n\nComputational Intelligence is thus a way of performing like human beings[citation needed]. Indeed, the characteristic of \"intelligence\" is usually attributed[by whom?] to humans. More recently, many products and items also claim to be \"intelligent\", an attribute which is directly linked to the reasoning and decision making[further explanation needed].\n\n"
    },
    {
      "title": "",
      "text": "The notion of Computational Intelligence was first used by the IEEE Neural Networks Council in 1990. This Council was founded in the 1980s by a group of researchers interested in the development of biological and artificial neural networks. On November 21, 2001, the IEEE Neural Networks Council became the IEEE Neural Networks Society, to become the IEEE Computational Intelligence Society two years later by including new areas of interest such as fuzzy systems and evolutionary computation, which they related to Computational Intelligence in 2011 (Dote and Ovaska).\n\nBut the first clear definition of Computational Intelligence was introduced by Bezdek in 1994:[1] a system is called computationally intelligent if it deals with low-level data such as numerical data, has a pattern-recognition component and does not use knowledge in the AI sense, and additionally when it begins to exhibit computational adaptively, fault tolerance, speed approaching human-like turnaround and error rates that approximate human performance.\n\nBezdek and Marks (1993) clearly differentiated CI from AI, by arguing that the first one is based on soft computing methods, whereas AI is based on hard computing ones.\n\n"
    },
    {
      "title": "Difference between Computational and Artificial Intelligence",
      "text": "Although Artificial Intelligence and Computational Intelligence seek a similar long-term goal: reach general intelligence, which is the intelligence of a machine that could perform any intellectual task that a human being can; there's a clear difference between them. According to Bezdek (1994), Computational Intelligence is a subset of Artificial Intelligence.\n\nThere are two types of machine intelligence: the artificial one based on hard computing techniques and the computational one based on soft computing methods, which enable adaptation to many situations.\n\nHard computing techniques work following binary logic based on only two values (the Booleans true or false, 0 or 1) on which modern computers are based. One problem with this logic is that our natural language cannot always be translated easily into absolute terms of 0 and 1. Soft computing techniques, based on fuzzy logic can be useful here.[6] Much closer to the way the human brain works by aggregating data to partial truths (Crisp/fuzzy systems), this logic is one of the main exclusive aspects of CI.\n\nWithin the same principles of fuzzy and binary logics follow crispy and fuzzy systems.[7] Crisp logic is a part of artificial intelligence principles and consists of either including an element in a set, or not, whereas fuzzy systems (CI) enable elements to be partially in a set. Following this logic, each element can be given a degree of membership (from 0 to 1) and not exclusively one of these 2 values.[8]\n\n"
    },
    {
      "title": "The five main principles of CI and its applications",
      "text": "The main applications of Computational Intelligence include computer science, engineering, data analysis and bio-medicine.\n\nAs explained before, fuzzy logic, one of CI's main principles, consists in measurements and process modelling made for real life's complex processes.[3] It can face incompleteness, and most importantly ignorance of data in a process model, contrarily to Artificial Intelligence, which requires exact knowledge.\n\nThis technique tends to apply to a wide range of domains such as control, image processing and decision making. But it is also well introduced in the field of household appliances with washing machines, microwave ovens, etc. We can face it too when using a video camera, where it helps stabilizing the image while holding the camera unsteadily. Other areas such as medical diagnostics, foreign exchange trading and business strategy selection are apart from this principle's numbers of applications.[1]\n\nFuzzy logic is mainly useful for approximate reasoning, and doesn't have learning abilities,[1] a qualification much needed that human beings have.[citation needed] It enables them to improve themselves by learning from their previous mistakes.\n\nThis is why CI experts work on the development of artificial neural networks based on the biological ones, which can be defined by 3 main components: the cell-body which processes the information, the axon, which is a device enabling the signal conducting, and the synapse, which controls signals. Therefore, artificial neural networks are doted of distributed information processing systems,[9] enabling the process and the learning from experiential data. Working like human beings, fault tolerance is also one of the main assets of this principle.[1]\n\nConcerning its applications, neural networks can be classified into five groups: data analysis and classification, associative memory, clustering generation of patterns and control.[1] Generally, this method aims to analyze and classify medical data, proceed to face and fraud detection, and most importantly deal with nonlinearities of a system in order to control it.[10] Furthermore, neural networks techniques share with the fuzzy logic ones the advantage of enabling data clustering.\n\nBased on the process of natural selection firstly introduced by Charles Robert Darwin, the evolutionary computation consists in capitalizing on the strength of natural evolution to bring up new artificial evolutionary methodologies.[11][page needed] It also includes other areas such as evolution strategy, and evolutionary algorithms which are seen as problem solvers... This principle's main applications cover areas such as optimization and multi-objective optimization, to which traditional mathematical one techniques aren't enough anymore to apply to a wide range of problems such as DNA Analysis, scheduling problems...[1]\n\nStill looking for a way of \"reasoning\" close to the humans' one, learning theory is one of the main approaches of CI. In psychology, learning is the process of bringing together cognitive, emotional and environmental effects and experiences to acquire, enhance or change knowledge, skills, values and world views (Ormrod, 1995; Illeris, 2004).[1] Learning theories then helps understanding how these effects and experiences are processed, and then helps making predictions based on previous experience.[12]\n\nBeing one of the main elements of fuzzy logic, probabilistic methods firstly introduced by Paul Erdos and Joel Spencer [1](1974), aim to evaluate the outcomes of a Computation Intelligent system, mostly defined by randomness.[13] Therefore, probabilistic methods bring out the possible solutions to a reasoning problem, based on prior knowledge.\n\n"
    }
  ],
  "links": []
}